msb_dynamic_crud/__init__.py
msb_dynamic_crud/msb_dynamic_crud.py
msb_dynamic_crud-0.0.6.dist-info/LICENSE
msb_dynamic_crud-0.0.6.dist-info/METADATA
msb_dynamic_crud-0.0.6.dist-info/WHEEL
msb_dynamic_crud-0.0.6.dist-info/top_level.txt
msb_dynamic_crud-0.0.6.dist-info/RECORD
